SCHdeepinsight/__init__.py
SCHdeepinsight/immune.py
SCHdeepinsight/pretrained_files_immune/img_transformer_immune.obj
SCHdeepinsight/pretrained_files_immune/label_encoder_immune_base.obj
SCHdeepinsight/pretrained_files_immune/label_encoder_immune_detailed.obj
SCHdeepinsight/pretrained_files_immune/minmax_scaler_immune.pkl
SCHdeepinsight/pretrained_files_immune/pretrained_genes_immune.csv
SCHdeepinsight/r_scripts/process_data.R
schdeepinsight-0.3.5.dist-info/METADATA
schdeepinsight-0.3.5.dist-info/WHEEL
schdeepinsight-0.3.5.dist-info/top_level.txt
schdeepinsight-0.3.5.dist-info/RECORD
