Metadata-Version: 2.2
Name: SCHdeepinsight
Version: 0.3.5
Summary: A tool for processing and hierarchically annotating immune scRNA-seq data with DeepInsight and CNN.
Home-page: https://github.com/shangruJia/scHDeepInsight
Author: Shangru JIA
Author-email: jiashangru@g.ecc.u-tokyo.ac.jp
Classifier: Programming Language :: Python :: 3
Classifier: License :: OSI Approved :: MIT License
Classifier: Operating System :: OS Independent
Requires-Python: >=3.6
Requires-Dist: anndata
Requires-Dist: pandas
Requires-Dist: numpy
Requires-Dist: scanpy
Requires-Dist: scipy
Requires-Dist: torch
Requires-Dist: torchvision
Requires-Dist: Pillow
Requires-Dist: efficientnet_pytorch
Requires-Dist: scikit-learn
Requires-Dist: opencv-python
Requires-Dist: huggingface_hub
Requires-Dist: rpy2
Dynamic: author
Dynamic: author-email
Dynamic: classifier
Dynamic: description
Dynamic: description-content-type
Dynamic: home-page
Dynamic: requires-dist
Dynamic: requires-python
Dynamic: summary
